docb/__init__.py
docb/document.py
docb/exceptions.py
docb/loading.py
docb/properties.py
docb/query.py
docb/testcase.py
docb/utils.py
docb/tests/__init__.py
docb/tests/documents.py
docb/tests/properties.py
docb/tests/utils.py
docb-1.1.2.dist-info/LICENSE
docb-1.1.2.dist-info/METADATA
docb-1.1.2.dist-info/WHEEL
docb-1.1.2.dist-info/top_level.txt
docb-1.1.2.dist-info/RECORD
