Metadata-Version: 2.1
Name: docb
Version: 1.1.2
Summary: Python ORM for DynamoDB
Home-page: https://github.com/capless/docb
Author: Brian Jinwright
Author-email: opensource@ipoots.com
Maintainer: Brian Jinwright
License: GPLv3
Keywords: dynamodb,orm
Platform: UNKNOWN
Classifier: Programming Language :: Python
Classifier: Topic :: Software Development :: Libraries :: Python Modules
Classifier: Environment :: Web Environment
Requires-Dist: boto3 (>=1.9.93)
Requires-Dist: envs (==1.3)
Requires-Dist: sammy (>=0.4.2)
Requires-Dist: valley (>=1.5.4)
Provides-Extra: test
Requires-Dist: coverage (>=4.1) ; extra == 'test'
Requires-Dist: envs (>=1.1.1) ; extra == 'test'
Requires-Dist: moto (>=1.3.4) ; extra == 'test'
Requires-Dist: nose (>=1.3.7) ; extra == 'test'
